canio/__init__.py
canio/auth.py
canio/config.py
canio/core.py
canio/helpers.py
canio/quality/__init__.py
canio/quality/basics.py
canio/quality/checks.py
canio/sources/__init__.py
canio/sources/csv.py
canio/sources/delta.py
canio/sources/mssql.py
canio/sources/parquet.py
canio-0.1.dist-info/LICENSE
canio-0.1.dist-info/METADATA
canio-0.1.dist-info/WHEEL
canio-0.1.dist-info/top_level.txt
canio-0.1.dist-info/RECORD
