Metadata-Version: 2.1
Name: canio
Version: 0.1
Summary: A package to simpify working data processing
Author: Morteza Hajipour
Author-email: mortezahajipour.works@gmail.com
License-File: LICENSE
